pytest_addons_test/__init__.py
pytest_addons_test-1.0.8.1.dist-info/entry_points.txt
pytest_addons_test-1.0.8.1.dist-info/WHEEL
pytest_addons_test-1.0.8.1.dist-info/METADATA
pytest_addons_test-1.0.8.1.dist-info/RECORD
